scriptmerge/__init__.py
scriptmerge/main.py
scriptmerge/merge_common.py
scriptmerge/merge_py.py
scriptmerge/merge_pyz.py
scriptmerge/prelude.py
scriptmerge/stdlib.py
scriptmerge-3.1.0.dist-info/METADATA
scriptmerge-3.1.0.dist-info/WHEEL
scriptmerge-3.1.0.dist-info/entry_points.txt
scriptmerge-3.1.0.dist-info/licenses/LICENSE
scriptmerge-3.1.0.dist-info/RECORD
