Metadata-Version: 2.3
Name: scriptmerge
Version: 3.1.0
Summary: Convert Python packages into a single script
Project-URL: Homepage, https://github.com/Amourspirit/python-scriptmerge/tree/scriptmerge
Project-URL: Documentation, https://github.com/Amourspirit/python-scriptmerge/wiki
Project-URL: Repository, https://github.com/Amourspirit/python-scriptmerge/tree/scriptmerge
Project-URL: Issues, https://github.com/Amourspirit/python-scriptmerge/tree/scriptmerge/issues
Author-email: ":Barry-Thomas-Paul: Moss" <bigbytetech@gmail.com>, Michael Williamson <mike@zwobble.org>
License: Copyright (c) 2012, Michael Williamson
Keywords: compile,oooscript,scriptmerge,stickytape
Classifier: Environment :: Console
Classifier: Intended Audience :: Developers
Classifier: License :: OSI Approved :: BSD License
Classifier: Operating System :: OS Independent
Classifier: Programming Language :: Python
Classifier: Programming Language :: Python :: 3.8
Classifier: Programming Language :: Python :: 3.9
Classifier: Programming Language :: Python :: 3.10
Classifier: Programming Language :: Python :: 3.11
Classifier: Programming Language :: Python :: 3.12
Classifier: Programming Language :: Python :: 3.13
Classifier: Topic :: Software Development
Classifier: Topic :: Software Development :: Libraries :: Python Modules
Classifier: Topic :: Utilities
Requires-Python: >=3.8
